[
  {
    "1998-2005 Statewide Standards of Learning Spring Assessment Results":"Shown in Percent Passing; Updated on 12/8/2005",
    "FIELD2":"",
    "FIELD3":"",
    "FIELD4":"",
    "FIELD5":"",
    "FIELD6":"",
    "FIELD7":"",
    "FIELD8":"",
    "FIELD9":"",
    "FIELD10":""
  },
  {
    "1998-2005 Statewide Standards of Learning Spring Assessment Results":"SOL Test",
    "FIELD2":"1998 Pass Rate",
    "FIELD3":"1999 Pass Rate",
    "FIELD4":"2000 Pass Rate",
    "FIELD5":"2001 Pass Rate",
    "FIELD6":"2002 Pass Rate",
    "FIELD7":"2003 Pass Rate",
    "FIELD8":"2004 Pass Rate",
    "FIELD9":"2005 Pass Rate",
    "FIELD10":"Change from 1998 to 2005"
  },
  {
    "1998-2005 Statewide Standards of Learning Spring Assessment Results":"Grade 3",
    "FIELD2":"",
    "FIELD3":"",
    "FIELD4":"",
    "FIELD5":"",
    "FIELD6":"",
    "FIELD7":"",
    "FIELD8":"",
    "FIELD9":"",
    "FIELD10":""
  },
  {
    "1998-2005 Statewide Standards of Learning Spring Assessment Results":"English: Reading",
    "FIELD2":"55",
    "FIELD3":"61",
    "FIELD4":"61",
    "FIELD5":"65",
    "FIELD6":"72",
    "FIELD7":"72",
    "FIELD8":"71",
    "FIELD9":"77",
    "FIELD10":"22"
  },
  {
    "1998-2005 Statewide Standards of Learning Spring Assessment Results":"Mathematics",
    "FIELD2":"63",
    "FIELD3":"68",
    "FIELD4":"71",
    "FIELD5":"77",
    "FIELD6":"80",
    "FIELD7":"83",
    "FIELD8":"87",
    "FIELD9":"87",
    "FIELD10":"24"
  },
  {
    "1998-2005 Statewide Standards of Learning Spring Assessment Results":"History & Social Science",
    "FIELD2":"49",
    "FIELD3":"62",
    "FIELD4":"65",
    "FIELD5":"72",
    "FIELD6":"76",
    "FIELD7":"82",
    "FIELD8":"87",
    "FIELD9":"89",
    "FIELD10":"40"
  },
  {
    "1998-2005 Statewide Standards of Learning Spring Assessment Results":"Science",
    "FIELD2":"63",
    "FIELD3":"68",
    "FIELD4":"73",
    "FIELD5":"74",
    "FIELD6":"78",
    "FIELD7":"82",
    "FIELD8":"85",
    "FIELD9":"89",
    "FIELD10":"26"
  },
  {
    "1998-2005 Statewide Standards of Learning Spring Assessment Results":"Grade 5",
    "FIELD2":"",
    "FIELD3":"",
    "FIELD4":"",
    "FIELD5":"",
    "FIELD6":"",
    "FIELD7":"",
    "FIELD8":"",
    "FIELD9":"",
    "FIELD10":""
  },
  {
    "1998-2005 Statewide Standards of Learning Spring Assessment Results":"English: Reading",
    "FIELD2":"68",
    "FIELD3":"69",
    "FIELD4":"68",
    "FIELD5":"73",
    "FIELD6":"78",
    "FIELD7":"82",
    "FIELD8":"85",
    "FIELD9":"85",
    "FIELD10":"17"
  },
  {
    "1998-2005 Statewide Standards of Learning Spring Assessment Results":"English: Writing",
    "FIELD2":"65",
    "FIELD3":"81",
    "FIELD4":"81",
    "FIELD5":"84",
    "FIELD6":"84",
    "FIELD7":"85",
    "FIELD8":"88",
    "FIELD9":"91",
    "FIELD10":"26"
  },
  {
    "1998-2005 Statewide Standards of Learning Spring Assessment Results":"Mathematics",
    "FIELD2":"47",
    "FIELD3":"51",
    "FIELD4":"63",
    "FIELD5":"67",
    "FIELD6":"71",
    "FIELD7":"74",
    "FIELD8":"78",
    "FIELD9":"80",
    "FIELD10":"33"
  },
  {
    "1998-2005 Statewide Standards of Learning Spring Assessment Results":"History & Social Science",
    "FIELD2":"33",
    "FIELD3":"46",
    "FIELD4":"51",
    "FIELD5":"63",
    "FIELD6":"72",
    "FIELD7":"79",
    "FIELD8":"86",
    "FIELD9":"85",
    "FIELD10":"52"
  },
  {
    "1998-2005 Statewide Standards of Learning Spring Assessment Results":"Science",
    "FIELD2":"59",
    "FIELD3":"67",
    "FIELD4":"64",
    "FIELD5":"75",
    "FIELD6":"76",
    "FIELD7":"79",
    "FIELD8":"84",
    "FIELD9":"81",
    "FIELD10":"22"
  },
  {
    "1998-2005 Statewide Standards of Learning Spring Assessment Results":"Grade 8",
    "FIELD2":"",
    "FIELD3":"",
    "FIELD4":"",
    "FIELD5":"",
    "FIELD6":"",
    "FIELD7":"",
    "FIELD8":"",
    "FIELD9":"",
    "FIELD10":""
  },
  {
    "1998-2005 Statewide Standards of Learning Spring Assessment Results":"English: Reading",
    "FIELD2":"65",
    "FIELD3":"67",
    "FIELD4":"70",
    "FIELD5":"73",
    "FIELD6":"69",
    "FIELD7":"68",
    "FIELD8":"72",
    "FIELD9":"76",
    "FIELD10":"11"
  },
  {
    "1998-2005 Statewide Standards of Learning Spring Assessment Results":"English: Writing",
    "FIELD2":"67",
    "FIELD3":"70",
    "FIELD4":"76",
    "FIELD5":"75",
    "FIELD6":"76",
    "FIELD7":"74",
    "FIELD8":"77",
    "FIELD9":"74",
    "FIELD10":"7"
  },
  {
    "1998-2005 Statewide Standards of Learning Spring Assessment Results":"Mathematics",
    "FIELD2":"53",
    "FIELD3":"60",
    "FIELD4":"61",
    "FIELD5":"68",
    "FIELD6":"71",
    "FIELD7":"73",
    "FIELD8":"78",
    "FIELD9":"78",
    "FIELD10":"25"
  },
  {
    "1998-2005 Statewide Standards of Learning Spring Assessment Results":"History & Social Science",
    "FIELD2":"35",
    "FIELD3":"40",
    "FIELD4":"50",
    "FIELD5":"56",
    "FIELD6":"78",
    "FIELD7":"80",
    "FIELD8":"83",
    "FIELD9":"81",
    "FIELD10":"46"
  },
  {
    "1998-2005 Statewide Standards of Learning Spring Assessment Results":"Science",
    "FIELD2":"71",
    "FIELD3":"78",
    "FIELD4":"82",
    "FIELD5":"84",
    "FIELD6":"85",
    "FIELD7":"84",
    "FIELD8":"88",
    "FIELD9":"87",
    "FIELD10":"16"
  },
  {
    "1998-2005 Statewide Standards of Learning Spring Assessment Results":"Content Specific ",
    "FIELD2":"",
    "FIELD3":"",
    "FIELD4":"",
    "FIELD5":"",
    "FIELD6":"",
    "FIELD7":"",
    "FIELD8":"",
    "FIELD9":"",
    "FIELD10":""
  },
  {
    "1998-2005 Statewide Standards of Learning Spring Assessment Results":"US History to 1877*",
    "FIELD2":"N/A",
    "FIELD3":"N/A",
    "FIELD4":"N/A",
    "FIELD5":"N/A",
    "FIELD6":"N/A",
    "FIELD7":"N/A",
    "FIELD8":"58",
    "FIELD9":"63",
    "FIELD10":"N/A"
  },
  {
    "1998-2005 Statewide Standards of Learning Spring Assessment Results":"US History from 1877 to Present*",
    "FIELD2":"N/A",
    "FIELD3":"N/A",
    "FIELD4":"N/A",
    "FIELD5":"N/A",
    "FIELD6":"N/A",
    "FIELD7":"N/A",
    "FIELD8":"76",
    "FIELD9":"84",
    "FIELD10":"N/A"
  },
  {
    "1998-2005 Statewide Standards of Learning Spring Assessment Results":"Civics & Economics*",
    "FIELD2":"N/A",
    "FIELD3":"N/A",
    "FIELD4":"N/A",
    "FIELD5":"N/A",
    "FIELD6":"N/A",
    "FIELD7":"N/A",
    "FIELD8":"81",
    "FIELD9":"84",
    "FIELD10":"N/A"
  },
  {
    "1998-2005 Statewide Standards of Learning Spring Assessment Results":"High School",
    "FIELD2":"",
    "FIELD3":"",
    "FIELD4":"",
    "FIELD5":"",
    "FIELD6":"",
    "FIELD7":"",
    "FIELD8":"",
    "FIELD9":"",
    "FIELD10":""
  },
  {
    "1998-2005 Statewide Standards of Learning Spring Assessment Results":"English: Reading",
    "FIELD2":"72",
    "FIELD3":"75",
    "FIELD4":"78",
    "FIELD5":"82",
    "FIELD6":"86",
    "FIELD7":"93",
    "FIELD8":"89",
    "FIELD9":"85",
    "FIELD10":"13"
  },
  {
    "1998-2005 Statewide Standards of Learning Spring Assessment Results":"English: Writing",
    "FIELD2":"71",
    "FIELD3":"81",
    "FIELD4":"85",
    "FIELD5":"84",
    "FIELD6":"86",
    "FIELD7":"91",
    "FIELD8":"87",
    "FIELD9":"88",
    "FIELD10":"17"
  },
  {
    "1998-2005 Statewide Standards of Learning Spring Assessment Results":"Algebra I",
    "FIELD2":"40",
    "FIELD3":"56",
    "FIELD4":"65",
    "FIELD5":"74",
    "FIELD6":"78",
    "FIELD7":"78",
    "FIELD8":"80",
    "FIELD9":"84",
    "FIELD10":"44"
  },
  {
    "1998-2005 Statewide Standards of Learning Spring Assessment Results":"Algebra II",
    "FIELD2":"31",
    "FIELD3":"51",
    "FIELD4":"58",
    "FIELD5":"74",
    "FIELD6":"77",
    "FIELD7":"81",
    "FIELD8":"86",
    "FIELD9":"87",
    "FIELD10":"56"
  },
  {
    "1998-2005 Statewide Standards of Learning Spring Assessment Results":"Geometry",
    "FIELD2":"52",
    "FIELD3":"62",
    "FIELD4":"67",
    "FIELD5":"73",
    "FIELD6":"76",
    "FIELD7":"79",
    "FIELD8":"82",
    "FIELD9":"81",
    "FIELD10":"29"
  },
  {
    "1998-2005 Statewide Standards of Learning Spring Assessment Results":"Virginia & US History",
    "FIELD2":"30",
    "FIELD3":"32",
    "FIELD4":"39",
    "FIELD5":"48",
    "FIELD6":"72",
    "FIELD7":"75",
    "FIELD8":"87",
    "FIELD9":"88",
    "FIELD10":"N/A"
  },
  {
    "1998-2005 Statewide Standards of Learning Spring Assessment Results":"World History & Geography to 1500**",
    "FIELD2":"62",
    "FIELD3":"68",
    "FIELD4":"75",
    "FIELD5":"83",
    "FIELD6":"86",
    "FIELD7":"86",
    "FIELD8":"83",
    "FIELD9":"82",
    "FIELD10":"N/A"
  },
  {
    "1998-2005 Statewide Standards of Learning Spring Assessment Results":"World History & Geography 1500 to Present**",
    "FIELD2":"41",
    "FIELD3":"47",
    "FIELD4":"60",
    "FIELD5":"65",
    "FIELD6":"79",
    "FIELD7":"82",
    "FIELD8":"83",
    "FIELD9":"86",
    "FIELD10":"N/A"
  },
  {
    "1998-2005 Statewide Standards of Learning Spring Assessment Results":"World Geography",
    "FIELD2":"N/A",
    "FIELD3":"N/A",
    "FIELD4":"76",
    "FIELD5":"77",
    "FIELD6":"74",
    "FIELD7":"76",
    "FIELD8":"71",
    "FIELD9":"70",
    "FIELD10":"N/A"
  },
  {
    "1998-2005 Statewide Standards of Learning Spring Assessment Results":"Earth Science",
    "FIELD2":"58",
    "FIELD3":"65",
    "FIELD4":"70",
    "FIELD5":"73",
    "FIELD6":"70",
    "FIELD7":"73",
    "FIELD8":"71",
    "FIELD9":"75",
    "FIELD10":"17"
  },
  {
    "1998-2005 Statewide Standards of Learning Spring Assessment Results":"Biology",
    "FIELD2":"72",
    "FIELD3":"81",
    "FIELD4":"79",
    "FIELD5":"81",
    "FIELD6":"83",
    "FIELD7":"82",
    "FIELD8":"80",
    "FIELD9":"79",
    "FIELD10":"7"
  },
  {
    "1998-2005 Statewide Standards of Learning Spring Assessment Results":"Chemistry",
    "FIELD2":"54",
    "FIELD3":"64",
    "FIELD4":"64",
    "FIELD5":"74",
    "FIELD6":"78",
    "FIELD7":"84",
    "FIELD8":"86",
    "FIELD9":"86",
    "FIELD10":"32"
  },
  {
    "1998-2005 Statewide Standards of Learning Spring Assessment Results":"* Content Specific tests first administered in 2004 for US History to 1877, US History from 1877 to Present, and Civics & Economics",
    "FIELD2":"",
    "FIELD3":"",
    "FIELD4":"",
    "FIELD5":"",
    "FIELD6":"",
    "FIELD7":"",
    "FIELD8":"",
    "FIELD9":"",
    "FIELD10":""
  },
  {
    "1998-2005 Statewide Standards of Learning Spring Assessment Results":"** 2004 end-of-course tests for Virginia & US History, World History & Geography to 1500, World History & Geography 1500 to Present, and World Geography based on 2001 revision of History/Social Science Standards of Learning. World Geography end-of-course test first administered in 2000.",
    "FIELD2":"",
    "FIELD3":"",
    "FIELD4":"",
    "FIELD5":"",
    "FIELD6":"",
    "FIELD7":"",
    "FIELD8":"",
    "FIELD9":"",
    "FIELD10":""
  },
  {
    "1998-2005 Statewide Standards of Learning Spring Assessment Results":"N/A -- Not available, Not applicable, or No longer given",
    "FIELD2":"",
    "FIELD3":"",
    "FIELD4":"",
    "FIELD5":"",
    "FIELD6":"",
    "FIELD7":"",
    "FIELD8":"",
    "FIELD9":"",
    "FIELD10":""
  },
  {
    "1998-2005 Statewide Standards of Learning Spring Assessment Results":"NOTE: Spring Pass rates do not include summer or fall results, but do include expedited retake results.",
    "FIELD2":"",
    "FIELD3":"",
    "FIELD4":"",
    "FIELD5":"",
    "FIELD6":"",
    "FIELD7":"",
    "FIELD8":"",
    "FIELD9":"",
    "FIELD10":""
  }
]
